pyhopper/__init__.py
pyhopper/cache.py
pyhopper/parallel.py
pyhopper/parameters.py
pyhopper/run_context.py
pyhopper/search.py
pyhopper/utils.py
pyhopper/callbacks/__init__.py
pyhopper/callbacks/aim.py
pyhopper/callbacks/callbacks.py
pyhopper/callbacks/mlflow.py
pyhopper/callbacks/tensorboard.py
pyhopper/callbacks/wandb.py
pyhopper/cancelers/__init__.py
pyhopper/cancelers/early_cancelers.py
pyhopper/cancellers/__init__.py
pyhopper/cancellers/early_cancellers.py
pyhopper/pruners/__init__.py
pyhopper/pruners/pruners.py
pyhopper-1.2.3.dist-info/LICENSE
pyhopper-1.2.3.dist-info/METADATA
pyhopper-1.2.3.dist-info/WHEEL
pyhopper-1.2.3.dist-info/top_level.txt
pyhopper-1.2.3.dist-info/RECORD
