Metadata-Version: 2.1
Name: pyhopper
Version: 1.2.3
Summary: TODO
Home-page: https://github.com/pyhopper/pyhopper
Author: Mathias Lechner and the PyHopper team
Author-email: mlech26l@gmail.com
License: Apache Software License (Apache 2.0)
Platform: UNKNOWN
Classifier: Programming Language :: Python
Classifier: Programming Language :: Python :: 3.6
Classifier: Operating System :: Unix
Classifier: Operating System :: Microsoft :: Windows
Classifier: Operating System :: MacOS
Classifier: Intended Audience :: Science/Research
Classifier: Topic :: Scientific/Engineering
Classifier: Topic :: Software Development
Requires-Python: >3.6.0
License-File: LICENSE
Requires-Dist: future
Requires-Dist: numpy
Requires-Dist: packaging
Requires-Dist: psutil
Requires-Dist: tqdm
